__init__.py
evgflip/__init__.py
evgflip/cli.py
evgflip/find_flips.py
evgflip/worker.py
evgflip-0.1.0.dist-info/LICENSE
evgflip-0.1.0.dist-info/METADATA
evgflip-0.1.0.dist-info/WHEEL
evgflip-0.1.0.dist-info/entry_points.txt
evgflip-0.1.0.dist-info/top_level.txt
evgflip-0.1.0.dist-info/RECORD
